diagonal_b6/__init__.py
diagonal_b6/api_generated.py
diagonal_b6/api_pb2.py
diagonal_b6/api_pb2_grpc.py
diagonal_b6/b6_test.py
diagonal_b6/connect.py
diagonal_b6/expression.py
diagonal_b6/features.py
diagonal_b6/generate_api.py
diagonal_b6/geometry.py
diagonal_b6/geometry_pb2.py
diagonal_b6/query.py
diagonal_b6-0.2.3.dist-info/METADATA
diagonal_b6-0.2.3.dist-info/WHEEL
diagonal_b6-0.2.3.dist-info/top_level.txt
diagonal_b6-0.2.3.dist-info/RECORD
