Metadata-Version: 2.1
Name: diagonal_b6
Version: 0.2.3
Summary: A Python client library for b6, Diagonal's geospatial analysis engine.
Author-email: Diagonal Works <hello@diagonal.works>
License: Apache License
Project-URL: Homepage, https://diagonal.works/b6
Classifier: Programming Language :: Python :: 3
Classifier: License :: OSI Approved :: Apache Software License
Classifier: Operating System :: OS Independent
Classifier: Development Status :: 3 - Alpha
Classifier: Topic :: Scientific/Engineering :: GIS
Requires-Python: >=3.10
Requires-Dist: grpcio >=1.43.0
Requires-Dist: protobuf >=3.14.0
Requires-Dist: s2sphere >=0.2.5
